django_tonnikala/__init__.py
django_tonnikala/backends.py
django_tonnikala/models.py
django_tonnikala-0.0.4.dist-info/METADATA
django_tonnikala-0.0.4.dist-info/WHEEL
django_tonnikala-0.0.4.dist-info/top_level.txt
django_tonnikala-0.0.4.dist-info/RECORD
