Metadata-Version: 2.1
Name: django-tonnikala
Version: 0.0.4
Summary: Django backend for Tonnikala templating language
Home-page: https://github.com/tetframework/django-tonnikala
Author: Rainer Koirikivi
Author-email: rainer@koirikivi.fi
License: UNKNOWN
Platform: UNKNOWN
Classifier: Framework :: Django
Classifier: License :: OSI Approved :: Apache Software License
Classifier: Programming Language :: Python
Classifier: Programming Language :: Python :: 2.6
Classifier: Programming Language :: Python :: 2.7
Classifier: Programming Language :: Python :: 3.3
Classifier: Programming Language :: Python :: 3.4
Classifier: Programming Language :: Python :: 3.5
Classifier: Programming Language :: Python :: 3.6
Classifier: Programming Language :: Python :: 3.7
Classifier: Programming Language :: Python :: Implementation :: CPython
Requires-Dist: tonnikala (>=1.0.0b1)
